{
  "guncelleme_zamani_utc": "2026-07-16T12:10:55.982636Z",
  "kaynak": "Yahoo Finance (yfinance) - birkac dakika gecikmeli, ANLIK DEGIL",
  "toplam_sembol": 30,
  "basarili_cekim": 30,
  "veriler": [
    {
      "sembol": "AKBNK",
      "son_fiyat": 67.55,
      "acilis": 67.65,
      "yuksek": 67.7,
      "dusuk": 67.45,
      "hacim": 2741571,
      "bar_zamani": "2026-07-16 14:45:00+03:00",
      "veri_kodu": "AKBNK",
      "kaynak_tip": "15m"
    },
    {
      "sembol": "YKBNK",
      "son_fiyat": 33.24,
      "acilis": 33.32,
      "yuksek": 33.34,
      "dusuk": 33.2,
      "hacim": 6694509,
      "bar_zamani": "2026-07-16 14:45:00+03:00",
      "veri_kodu": "YKBNK",
      "kaynak_tip": "15m"
    },
    {
      "sembol": "GARAN",
      "son_fiyat": 127.4,
      "acilis": 127.5,
      "yuksek": 127.6,
      "dusuk": 127.1,
      "hacim": 398168,
      "bar_zamani": "2026-07-16 14:45:00+03:00",
      "veri_kodu": "GARAN",
      "kaynak_tip": "15m"
    },
    {
      "sembol": "ISCTR",
      "son_fiyat": 13.67,
      "acilis": 13.69,
      "yuksek": 13.7,
      "dusuk": 13.63,
      "hacim": 12124431,
      "bar_zamani": "2026-07-16 14:45:00+03:00",
      "veri_kodu": "ISCTR",
      "kaynak_tip": "15m"
    },
    {
      "sembol": "SAHOL",
      "son_fiyat": 90.1,
      "acilis": 90.1,
      "yuksek": 90.15,
      "dusuk": 89.9,
      "hacim": 838561,
      "bar_zamani": "2026-07-16 14:45:00+03:00",
      "veri_kodu": "SAHOL",
      "kaynak_tip": "15m"
    },
    {
      "sembol": "KCHOL",
      "son_fiyat": 195.7,
      "acilis": 195.4,
      "yuksek": 195.7,
      "dusuk": 194.9,
      "hacim": 353728,
      "bar_zamani": "2026-07-16 14:45:00+03:00",
      "veri_kodu": "KCHOL",
      "kaynak_tip": "15m"
    },
    {
      "sembol": "THYAO",
      "son_fiyat": 332.0,
      "acilis": 331.75,
      "yuksek": 332.0,
      "dusuk": 331.0,
      "hacim": 341582,
      "bar_zamani": "2026-07-16 14:45:00+03:00",
      "veri_kodu": "THYAO",
      "kaynak_tip": "15m"
    },
    {
      "sembol": "TAVHL",
      "son_fiyat": 263.0,
      "acilis": 263.5,
      "yuksek": 263.5,
      "dusuk": 262.5,
      "hacim": 41871,
      "bar_zamani": "2026-07-16 14:45:00+03:00",
      "veri_kodu": "TAVHL",
      "kaynak_tip": "15m"
    },
    {
      "sembol": "EREGL",
      "son_fiyat": 43.84,
      "acilis": 43.92,
      "yuksek": 43.94,
      "dusuk": 43.84,
      "hacim": 847238,
      "bar_zamani": "2026-07-16 14:45:00+03:00",
      "veri_kodu": "EREGL",
      "kaynak_tip": "15m"
    },
    {
      "sembol": "ASELS",
      "son_fiyat": 359.25,
      "acilis": 359.5,
      "yuksek": 359.75,
      "dusuk": 358.5,
      "hacim": 351315,
      "bar_zamani": "2026-07-16 14:45:00+03:00",
      "veri_kodu": "ASELS",
      "kaynak_tip": "15m"
    },
    {
      "sembol": "ASTOR",
      "son_fiyat": 321.75,
      "acilis": 322.75,
      "yuksek": 322.75,
      "dusuk": 321.25,
      "hacim": 301543,
      "bar_zamani": "2026-07-16 14:45:00+03:00",
      "veri_kodu": "ASTOR",
      "kaynak_tip": "15m"
    },
    {
      "sembol": "MGROS",
      "son_fiyat": 625.0,
      "acilis": 625.0,
      "yuksek": 625.5,
      "dusuk": 624.0,
      "hacim": 31353,
      "bar_zamani": "2026-07-16 14:45:00+03:00",
      "veri_kodu": "MGROS",
      "kaynak_tip": "15m"
    },
    {
      "sembol": "BIMAS",
      "son_fiyat": 396.25,
      "acilis": 396.0,
      "yuksek": 396.25,
      "dusuk": 395.25,
      "hacim": 241586,
      "bar_zamani": "2026-07-16 14:45:00+03:00",
      "veri_kodu": "BIMAS",
      "kaynak_tip": "15m"
    },
    {
      "sembol": "TUPRS",
      "son_fiyat": 277.25,
      "acilis": 277.25,
      "yuksek": 277.5,
      "dusuk": 276.75,
      "hacim": 378244,
      "bar_zamani": "2026-07-16 14:45:00+03:00",
      "veri_kodu": "TUPRS",
      "kaynak_tip": "15m"
    },
    {
      "sembol": "TOASO",
      "son_fiyat": 299.5,
      "acilis": 300.25,
      "yuksek": 300.5,
      "dusuk": 299.5,
      "hacim": 34133,
      "bar_zamani": "2026-07-16 14:45:00+03:00",
      "veri_kodu": "TOASO",
      "kaynak_tip": "15m"
    },
    {
      "sembol": "FROTO",
      "son_fiyat": 84.45,
      "acilis": 84.35,
      "yuksek": 84.45,
      "dusuk": 84.15,
      "hacim": 343606,
      "bar_zamani": "2026-07-16 14:45:00+03:00",
      "veri_kodu": "FROTO",
      "kaynak_tip": "15m"
    },
    {
      "sembol": "ENKAI",
      "son_fiyat": 91.2,
      "acilis": 91.25,
      "yuksek": 91.3,
      "dusuk": 91.1,
      "hacim": 68858,
      "bar_zamani": "2026-07-16 14:45:00+03:00",
      "veri_kodu": "ENKAI",
      "kaynak_tip": "15m"
    },
    {
      "sembol": "TTKOM",
      "son_fiyat": 58.4,
      "acilis": 58.4,
      "yuksek": 58.45,
      "dusuk": 58.25,
      "hacim": 898785,
      "bar_zamani": "2026-07-16 14:45:00+03:00",
      "veri_kodu": "TTKOM",
      "kaynak_tip": "15m"
    },
    {
      "sembol": "AEFES",
      "son_fiyat": 20.62,
      "acilis": 20.64,
      "yuksek": 20.66,
      "dusuk": 20.6,
      "hacim": 665688,
      "bar_zamani": "2026-07-16 14:45:00+03:00",
      "veri_kodu": "AEFES",
      "kaynak_tip": "15m"
    },
    {
      "sembol": "PGSUS",
      "son_fiyat": 168.5,
      "acilis": 168.5,
      "yuksek": 168.7,
      "dusuk": 168.2,
      "hacim": 216589,
      "bar_zamani": "2026-07-16 14:45:00+03:00",
      "veri_kodu": "PGSUS",
      "kaynak_tip": "15m"
    },
    {
      "sembol": "HALKB",
      "son_fiyat": 39.28,
      "acilis": 39.32,
      "yuksek": 39.32,
      "dusuk": 39.22,
      "hacim": 707003,
      "bar_zamani": "2026-07-16 14:45:00+03:00",
      "veri_kodu": "HALKB",
      "kaynak_tip": "15m"
    },
    {
      "sembol": "VAKBN",
      "son_fiyat": 31.14,
      "acilis": 31.12,
      "yuksek": 31.14,
      "dusuk": 31.0,
      "hacim": 876910,
      "bar_zamani": "2026-07-16 14:45:00+03:00",
      "veri_kodu": "VAKBN",
      "kaynak_tip": "15m"
    },
    {
      "sembol": "OTKAR",
      "son_fiyat": 332.75,
      "acilis": 333.25,
      "yuksek": 333.25,
      "dusuk": 332.5,
      "hacim": 3965,
      "bar_zamani": "2026-07-16 14:45:00+03:00",
      "veri_kodu": "OTKAR",
      "kaynak_tip": "15m"
    },
    {
      "sembol": "PETKM",
      "son_fiyat": 20.4,
      "acilis": 20.32,
      "yuksek": 20.4,
      "dusuk": 20.28,
      "hacim": 2640938,
      "bar_zamani": "2026-07-16 14:45:00+03:00",
      "veri_kodu": "PETKM",
      "kaynak_tip": "15m"
    },
    {
      "sembol": "SISE",
      "son_fiyat": 44.96,
      "acilis": 44.86,
      "yuksek": 44.96,
      "dusuk": 44.82,
      "hacim": 764369,
      "bar_zamani": "2026-07-16 14:45:00+03:00",
      "veri_kodu": "SISE",
      "kaynak_tip": "15m"
    },
    {
      "sembol": "EKGYO",
      "son_fiyat": 21.06,
      "acilis": 21.16,
      "yuksek": 21.16,
      "dusuk": 21.04,
      "hacim": 1634241,
      "bar_zamani": "2026-07-16 14:45:00+03:00",
      "veri_kodu": "EKGYO",
      "kaynak_tip": "15m"
    },
    {
      "sembol": "TRMET",
      "son_fiyat": 121.4,
      "acilis": 121.3,
      "yuksek": 121.4,
      "dusuk": 121.1,
      "hacim": 63426,
      "bar_zamani": "2026-07-16 14:45:00+03:00",
      "veri_kodu": "TRMET",
      "kaynak_tip": "15m"
    },
    {
      "sembol": "ALARK",
      "son_fiyat": 101.5,
      "acilis": 101.5,
      "yuksek": 101.6,
      "dusuk": 101.3,
      "hacim": 84547,
      "bar_zamani": "2026-07-16 14:45:00+03:00",
      "veri_kodu": "ALARK",
      "kaynak_tip": "15m"
    },
    {
      "sembol": "ENJSA",
      "son_fiyat": 100.7,
      "acilis": 100.8,
      "yuksek": 100.8,
      "dusuk": 100.5,
      "hacim": 28051,
      "bar_zamani": "2026-07-16 14:45:00+03:00",
      "veri_kodu": "ENJSA",
      "kaynak_tip": "15m"
    },
    {
      "sembol": "ULKER",
      "son_fiyat": 98.6,
      "acilis": 98.8,
      "yuksek": 98.8,
      "dusuk": 98.5,
      "hacim": 97491,
      "bar_zamani": "2026-07-16 14:45:00+03:00",
      "veri_kodu": "ULKER",
      "kaynak_tip": "15m"
    }
  ]
}